src/__init__.py
src/uniqchars2/__init__.py
src/uniqchars2/main.py
src/uniqchars2/app/__init__.py
src/uniqchars2/app/app.py
src/uniqchars2/utils/__init__.py
src/uniqchars2/utils/exceptions.py
src/uniqchars2/utils/functions.py
tests/__init__.py
uniqchars2-1.3.dist-info/LICENSE
uniqchars2-1.3.dist-info/METADATA
uniqchars2-1.3.dist-info/WHEEL
uniqchars2-1.3.dist-info/entry_points.txt
uniqchars2-1.3.dist-info/top_level.txt
uniqchars2-1.3.dist-info/RECORD
